{
  "hero_title": "Debug выгорания",
  "hero_subtitle": "50 историй IT-фениксов, которые прошли через кризис и вернулись сильнее.",
  "hero_cta_primary": {
    "text": "Стать героем книги",
    "href": "/join"
  },
  "hero_cta_secondary": {
    "text": "Посмотреть героев",
    "href": "/heroes"
  },
  "about_manifesto": {
    "title": "Почему появилась эта книга",
    "intro": [
      "Выгорание — не слабость. Это побочный эффект ответственности, амбиций и постоянного напряжения.",
      "Эта книга — про сильных IT-людей, которые долго держались, игнорировали сигналы и однажды оказались в точке «дальше так нельзя». И смогли пройти через это."
    ],
    "final_line": "Это не советы. Это опыт."
  },
  "about_features": [
    {
      "title": "50 реальных историй",
      "text": "Без «правильных» ответов и глянца"
    },
    {
      "title": "Разные роли и компании",
      "text": "Dev / QA / PM / Design / Founders"
    },
    {
      "title": "Честные переживания",
      "text": "Без цензуры и морализаторства"
    },
    {
      "title": "Психологический разбор",
      "text": "Выводы и опоры после каждой истории"
    }
  ],
  "featured_count": 6,
  "join_cta_title": "Хочешь стать героем книги?",
  "join_cta_bullets": [
    "Интервью 60 минут — бережный формат",
    "Мы пишем и редактируем главу за тебя",
    "Поддержка, комьюнити и пиар"
  ],
  "join_cta_button": {
    "text": "Подать заявку",
    "href": "/join"
  }
}
